discordwebhook/__init__.py
discordwebhook/discordwebhook.py
discordwebhook-1.0.3.dist-info/LICENSE.txt
discordwebhook-1.0.3.dist-info/METADATA
discordwebhook-1.0.3.dist-info/WHEEL
discordwebhook-1.0.3.dist-info/top_level.txt
discordwebhook-1.0.3.dist-info/RECORD
