Metadata-Version: 2.1
Name: discordwebhook
Version: 1.0.3
Summary: discordwebhlok is a python library         for discord webhook with discord rest api on Python 3.6 and above.
Home-page: https://github.com/10mohi6/discord-webhook-python
Author: 10mohi6
Author-email: 10.mohi.6.y@gmail.com
License: MIT
Keywords: discord webhook api python
Platform: UNKNOWN
Classifier: Development Status :: 5 - Production/Stable
Classifier: Programming Language :: Python
Classifier: Programming Language :: Python :: 3
Classifier: Programming Language :: Python :: 3.6
Classifier: Programming Language :: Python :: 3.7
Classifier: Programming Language :: Python :: 3.8
Classifier: Programming Language :: Python :: 3.9
Classifier: Intended Audience :: Developers
Classifier: Topic :: Communications :: Chat
Classifier: Topic :: System :: Networking
Classifier: Topic :: Office/Business
Classifier: License :: OSI Approved :: MIT License
Requires-Python: >=3.6.0
License-File: LICENSE.txt
